{
  "count": 5,
  "start": 0,
  "total": 27,
  "subjects": [
    {
      "rating": {
        "max": 10,
        "average": 7.6,
        "stars": "40",
        "min": 0
      },
      "genres": [
        "\u559c\u5267"
      ],
      "title": "\u7f9e\u7f9e\u7684\u94c1\u62f3",
      "casts": [
        {
          "alt": "https:\/\/movie.douban.com\/celebrity\/1350408\/",
          "avatars": {
            "small": "https://img3.doubanio.com\/img\/celebrity\/small\/1437031126.82.jpg",
            "large": "https://img3.doubanio.com\/img\/celebrity\/large\/1437031126.82.jpg",
            "medium": "https://img3.doubanio.com\/img\/celebrity\/medium\/1437031126.82.jpg"
          },
          "name": "\u827e\u4f26",
          "id": "1350408"
        },
        {
          "alt": "https:\/\/movie.douban.com\/celebrity\/1319032\/",
          "avatars": {
            "small": "https://img3.doubanio.com\/img\/celebrity\/small\/1444800807.11.jpg",
            "large": "https://img3.doubanio.com\/img\/celebrity\/large\/1444800807.11.jpg",
            "medium": "https://img3.doubanio.com\/img\/celebrity\/medium\/1444800807.11.jpg"
          },
          "name": "\u9a6c\u4e3d",
          "id": "1319032"
        },
        {
          "alt": "https:\/\/movie.douban.com\/celebrity\/1325700\/",
          "avatars": {
            "small": "https://img1.doubanio.com\/img\/celebrity\/small\/1356510694.28.jpg",
            "large": "https://img1.doubanio.com\/img\/celebrity\/large\/1356510694.28.jpg",
            "medium": "https://img1.doubanio.com\/img\/celebrity\/medium\/1356510694.28.jpg"
          },
          "name": "\u6c88\u817e",
          "id": "1325700"
        }
      ],
      "collect_count": 36032,
      "original_title": "\u7f9e\u7f9e\u7684\u94c1\u62f3",
      "subtype": "movie",
      "directors": [
        {
          "alt": "https:\/\/movie.douban.com\/celebrity\/1350407\/",
          "avatars": {
            "small": "https://img3.doubanio.com\/img\/celebrity\/small\/1437031175.04.jpg",
            "large": "https://img3.doubanio.com\/img\/celebrity\/large\/1437031175.04.jpg",
            "medium": "https://img3.doubanio.com\/img\/celebrity\/medium\/1437031175.04.jpg"
          },
          "name": "\u5b8b\u9633",
          "id": "1350407"
        },
        {
          "alt": "https:\/\/movie.douban.com\/celebrity\/1381643\/",
          "avatars": {
            "small": "https://img3.doubanio.com\/img\/celebrity\/small\/1506162881.51.jpg",
            "large": "https://img3.doubanio.com\/img\/celebrity\/large\/1506162881.51.jpg",
            "medium": "https://img3.doubanio.com\/img\/celebrity\/medium\/1506162881.51.jpg"
          },
          "name": "\u5f20\u5403\u9c7c",
          "id": "1381643"
        }
      ],
      "year": "2017",
      "images": {
        "small": "https://img1.doubanio.com\/view\/movie_poster_cover\/ipst\/public\/p2499793218.webp",
        "large": "https://img1.doubanio.com\/view\/movie_poster_cover\/lpst\/public\/p2499793218.webp",
        "medium": "https://img1.doubanio.com\/view\/movie_poster_cover\/spst\/public\/p2499793218.webp"
      },
      "alt": "https:\/\/movie.douban.com\/subject\/27038183\/",
      "id": "27038183"
    },
    {
      "rating": {
        "max": 10,
        "average": 7.4,
        "stars": "40",
        "min": 0
      },
      "genres": [
        "\u52a8\u4f5c",
        "\u60ca\u609a"
      ],
      "title": "\u82f1\u4f26\u5bf9\u51b3",
      "casts": [
        {
          "alt": "https:\/\/movie.douban.com\/celebrity\/1054531\/",
          "avatars": {
            "small": "https://img3.doubanio.com\/img\/celebrity\/small\/694.jpg",
            "large": "https://img3.doubanio.com\/img\/celebrity\/large\/694.jpg",
            "medium": "https://img3.doubanio.com\/img\/celebrity\/medium\/694.jpg"
          },
          "name": "\u6210\u9f99",
          "id": "1054531"
        },
        {
          "alt": "https:\/\/movie.douban.com\/celebrity\/1031219\/",
          "avatars": {
            "small": "https://img1.doubanio.com\/img\/celebrity\/small\/50837.jpg",
            "large": "https://img1.doubanio.com\/img\/celebrity\/large\/50837.jpg",
            "medium": "https://img1.doubanio.com\/img\/celebrity\/medium\/50837.jpg"
          },
          "name": "\u76ae\u5c14\u65af\u00b7\u5e03\u9c81\u65af\u5357",
          "id": "1031219"
        },
        {
          "alt": "https:\/\/movie.douban.com\/celebrity\/1011562\/",
          "avatars": {
            "small": "https://img3.doubanio.com\/img\/celebrity\/small\/1415689928.93.jpg",
            "large": "https://img3.doubanio.com\/img\/celebrity\/large\/1415689928.93.jpg",
            "medium": "https://img3.doubanio.com\/img\/celebrity\/medium\/1415689928.93.jpg"
          },
          "name": "\u5218\u6d9b",
          "id": "1011562"
        }
      ],
      "collect_count": 15137,
      "original_title": "The Foreigner",
      "subtype": "movie",
      "directors": [
        {
          "alt": "https:\/\/movie.douban.com\/celebrity\/1040630\/",
          "avatars": {
            "small": "https://img3.doubanio.com\/img\/celebrity\/small\/10682.jpg",
            "large": "https://img3.doubanio.com\/img\/celebrity\/large\/10682.jpg",
            "medium": "https://img3.doubanio.com\/img\/celebrity\/medium\/10682.jpg"
          },
          "name": "\u9a6c\u4e01\u00b7\u574e\u8d1d\u5c14",
          "id": "1040630"
        }
      ],
      "year": "2017",
      "images": {
        "small": "https://img3.doubanio.com\/view\/movie_poster_cover\/ipst\/public\/p2499135561.webp",
        "large": "https://img3.doubanio.com\/view\/movie_poster_cover\/lpst\/public\/p2499135561.webp",
        "medium": "https://img3.doubanio.com\/view\/movie_poster_cover\/spst\/public\/p2499135561.webp"
      },
      "alt": "https:\/\/movie.douban.com\/subject\/25723583\/",
      "id": "25723583"
    },
    {
      "rating": {
        "max": 10,
        "average": 7.6,
        "stars": "40",
        "min": 0
      },
      "genres": [
        "\u52a8\u4f5c",
        "\u72af\u7f6a"
      ],
      "title": "\u8ffd\u9f99",
      "casts": [
        {
          "alt": "https:\/\/movie.douban.com\/celebrity\/1025194\/",
          "avatars": {
            "small": "https://img3.doubanio.com\/img\/celebrity\/small\/10695.jpg",
            "large": "https://img3.doubanio.com\/img\/celebrity\/large\/10695.jpg",
            "medium": "https://img3.doubanio.com\/img\/celebrity\/medium\/10695.jpg"
          },
          "name": "\u7504\u5b50\u4e39",
          "id": "1025194"
        },
        {
          "alt": "https:\/\/movie.douban.com\/celebrity\/1054424\/",
          "avatars": {
            "small": "https://img3.doubanio.com\/img\/celebrity\/small\/1378956633.91.jpg",
            "large": "https://img3.doubanio.com\/img\/celebrity\/large\/1378956633.91.jpg",
            "medium": "https://img3.doubanio.com\/img\/celebrity\/medium\/1378956633.91.jpg"
          },
          "name": "\u5218\u5fb7\u534e",
          "id": "1054424"
        },
        {
          "alt": "https:\/\/movie.douban.com\/celebrity\/1317884\/",
          "avatars": {
            "small": "https://img1.doubanio.com\/img\/celebrity\/small\/1488637169.38.jpg",
            "large": "https://img1.doubanio.com\/img\/celebrity\/large\/1488637169.38.jpg",
            "medium": "https://img1.doubanio.com\/img\/celebrity\/medium\/1488637169.38.jpg"
          },
          "name": "\u59dc\u7693\u6587",
          "id": "1317884"
        }
      ],
      "collect_count": 8986,
      "original_title": "\u8ffd\u9f8d",
      "subtype": "movie",
      "directors": [
        {
          "alt": "https:\/\/movie.douban.com\/celebrity\/1274331\/",
          "avatars": {
            "small": "https://img1.doubanio.com\/img\/celebrity\/small\/3237.jpg",
            "large": "https://img1.doubanio.com\/img\/celebrity\/large\/3237.jpg",
            "medium": "https://img1.doubanio.com\/img\/celebrity\/medium\/3237.jpg"
          },
          "name": "\u738b\u6676",
          "id": "1274331"
        },
        {
          "alt": "https:\/\/movie.douban.com\/celebrity\/1318237\/",
          "avatars": {
            "small": "https://img1.doubanio.com\/img\/celebrity\/small\/1475727461.38.jpg",
            "large": "https://img1.doubanio.com\/img\/celebrity\/large\/1475727461.38.jpg",
            "medium": "https://img1.doubanio.com\/img\/celebrity\/medium\/1475727461.38.jpg"
          },
          "name": "\u5173\u667a\u8000",
          "id": "1318237"
        }
      ],
      "year": "2017",
      "images": {
        "small": "https://img3.doubanio.com\/view\/movie_poster_cover\/ipst\/public\/p2499052494.webp",
        "large": "https://img3.doubanio.com\/view\/movie_poster_cover\/lpst\/public\/p2499052494.webp",
        "medium": "https://img3.doubanio.com\/view\/movie_poster_cover\/spst\/public\/p2499052494.webp"
      },
      "alt": "https:\/\/movie.douban.com\/subject\/26425068\/",
      "id": "26425068"
    },
    {
      "rating": {
        "max": 10,
        "average": 4.9,
        "stars": "25",
        "min": 0
      },
      "genres": [
        "\u5267\u60c5",
        "\u52a8\u4f5c",
        "\u6218\u4e89"
      ],
      "title": "\u7a7a\u5929\u730e",
      "casts": [
        {
          "alt": "https:\/\/movie.douban.com\/celebrity\/1274252\/",
          "avatars": {
            "small": "https://img3.doubanio.com\/img\/celebrity\/small\/1475913973.94.jpg",
            "large": "https://img3.doubanio.com\/img\/celebrity\/large\/1475913973.94.jpg",
            "medium": "https://img3.doubanio.com\/img\/celebrity\/medium\/1475913973.94.jpg"
          },
          "name": "\u674e\u6668",
          "id": "1274252"
        },
        {
          "alt": "https:\/\/movie.douban.com\/celebrity\/1050059\/",
          "avatars": {
            "small": "https://img3.doubanio.com\/img\/celebrity\/small\/1691.jpg",
            "large": "https://img3.doubanio.com\/img\/celebrity\/large\/1691.jpg",
            "medium": "https://img3.doubanio.com\/img\/celebrity\/medium\/1691.jpg"
          },
          "name": "\u8303\u51b0\u51b0",
          "id": "1050059"
        },
        {
          "alt": "https:\/\/movie.douban.com\/celebrity\/1314827\/",
          "avatars": {
            "small": "https://img1.doubanio.com\/img\/celebrity\/small\/1445948736.67.jpg",
            "large": "https://img1.doubanio.com\/img\/celebrity\/large\/1445948736.67.jpg",
            "medium": "https://img1.doubanio.com\/img\/celebrity\/medium\/1445948736.67.jpg"
          },
          "name": "\u738b\u5343\u6e90",
          "id": "1314827"
        }
      ],
      "collect_count": 12096,
      "original_title": "\u7a7a\u5929\u730e",
      "subtype": "movie",
      "directors": [
        {
          "alt": "https:\/\/movie.douban.com\/celebrity\/1274252\/",
          "avatars": {
            "small": "https://img3.doubanio.com\/img\/celebrity\/small\/1475913973.94.jpg",
            "large": "https://img3.doubanio.com\/img\/celebrity\/large\/1475913973.94.jpg",
            "medium": "https://img3.doubanio.com\/img\/celebrity\/medium\/1475913973.94.jpg"
          },
          "name": "\u674e\u6668",
          "id": "1274252"
        }
      ],
      "year": "2017",
      "images": {
        "small": "https://img1.doubanio.com\/view\/movie_poster_cover\/ipst\/public\/p2499163778.webp",
        "large": "https://img1.doubanio.com\/view\/movie_poster_cover\/lpst\/public\/p2499163778.webp",
        "medium": "https://img1.doubanio.com\/view\/movie_poster_cover\/spst\/public\/p2499163778.webp"
      },
      "alt": "https:\/\/movie.douban.com\/subject\/26753020\/",
      "id": "26753020"
    },
    {
      "rating": {
        "max": 10,
        "average": 6.9,
        "stars": "35",
        "min": 0
      },
      "genres": [
        "\u559c\u5267",
        "\u97f3\u4e50"
      ],
      "title": "\u7f1d\u7eab\u673a\u4e50\u961f",
      "casts": [
        {
          "alt": "https:\/\/movie.douban.com\/celebrity\/1324043\/",
          "avatars": {
            "small": "https://img3.doubanio.com\/img\/celebrity\/small\/1490342249.11.jpg",
            "large": "https://img3.doubanio.com\/img\/celebrity\/large\/1490342249.11.jpg",
            "medium": "https://img3.doubanio.com\/img\/celebrity\/medium\/1490342249.11.jpg"
          },
          "name": "\u5927\u9e4f",
          "id": "1324043"
        },
        {
          "alt": "https:\/\/movie.douban.com\/celebrity\/1316368\/",
          "avatars": {
            "small": "https://img3.doubanio.com\/img\/celebrity\/small\/1473410979.5.jpg",
            "large": "https://img3.doubanio.com\/img\/celebrity\/large\/1473410979.5.jpg",
            "medium": "https://img3.doubanio.com\/img\/celebrity\/medium\/1473410979.5.jpg"
          },
          "name": "\u4e54\u6749",
          "id": "1316368"
        },
        {
          "alt": "https:\/\/movie.douban.com\/celebrity\/1315729\/",
          "avatars": {
            "small": "https://img3.doubanio.com\/img\/celebrity\/small\/1441515551.6.jpg",
            "large": "https://img3.doubanio.com\/img\/celebrity\/large\/1441515551.6.jpg",
            "medium": "https://img3.doubanio.com\/img\/celebrity\/medium\/1441515551.6.jpg"
          },
          "name": "\u53e4\u529b\u5a1c\u624e",
          "id": "1315729"
        }
      ],
      "collect_count": 14422,
      "original_title": "\u7f1d\u7eab\u673a\u4e50\u961f",
      "subtype": "movie",
      "directors": [
        {
          "alt": "https:\/\/movie.douban.com\/celebrity\/1324043\/",
          "avatars": {
            "small": "https://img3.doubanio.com\/img\/celebrity\/small\/1490342249.11.jpg",
            "large": "https://img3.doubanio.com\/img\/celebrity\/large\/1490342249.11.jpg",
            "medium": "https://img3.doubanio.com\/img\/celebrity\/medium\/1490342249.11.jpg"
          },
          "name": "\u5927\u9e4f",
          "id": "1324043"
        }
      ],
      "year": "2017",
      "images": {
        "small": "https://img3.doubanio.com\/view\/movie_poster_cover\/ipst\/public\/p2498558511.webp",
        "large": "https://img3.doubanio.com\/view\/movie_poster_cover\/lpst\/public\/p2498558511.webp",
        "medium": "https://img3.doubanio.com\/view\/movie_poster_cover\/spst\/public\/p2498558511.webp"
      },
      "alt": "https:\/\/movie.douban.com\/subject\/26926321\/",
      "id": "26926321"
    }
  ],
  "title": "\u6b63\u5728\u4e0a\u6620\u7684\u7535\u5f71-\u5317\u4eac"
}